yaqc_cmds/VERSION
yaqc_cmds/__init__.py
yaqc_cmds/__main__.py
yaqc_cmds/__version__.py
yaqc_cmds/_main_window.py
yaqc_cmds/_plot.py
yaqc_cmds/config-template.toml
yaqc_cmds/hardware/__init__.py
yaqc_cmds/hardware/delays.py
yaqc_cmds/hardware/filters.py
yaqc_cmds/hardware/hardware.py
yaqc_cmds/hardware/opas.py
yaqc_cmds/hardware/spectrometers.py
yaqc_cmds/project/__init__.py
yaqc_cmds/project/classes.py
yaqc_cmds/project/file_dialog_handler.py
yaqc_cmds/project/kit.py
yaqc_cmds/project/logging_handler.py
yaqc_cmds/project/project_globals.py
yaqc_cmds/project/style.py
yaqc_cmds/project/widgets.py
yaqc_cmds/project/slack/.gitignore
yaqc_cmds/project/slack/__init__.py
yaqc_cmds/project/slack/bots.py
yaqc_cmds/project/slack/rtmbot.py
yaqc_cmds/project/slack/slack.py
yaqc_cmds/project/slack/test_slack.py
yaqc_cmds/project/widget files/checkbox_checked.png
yaqc_cmds/project/widget files/checkbox_unchecked.png
yaqc_cmds/sensors/__init__.py
yaqc_cmds/sensors/_sensors.py
yaqc_cmds/sensors/signals.py
yaqc_cmds/somatic/__init__.py
yaqc_cmds/somatic/_wt5.py
yaqc_cmds/somatic/acquisition.py
yaqc_cmds/somatic/constant_resolver.py
yaqc_cmds/somatic/queue.py
yaqc_cmds/somatic/signals.py
yaqc_cmds/somatic/modules/abstract_tuning.py
yaqc_cmds/somatic/modules/home.py
yaqc_cmds/somatic/modules/motortune.py
yaqc_cmds/somatic/modules/scan.py
yaqc_cmds/somatic/modules/set_shutter.py
yaqc_cmds/somatic/modules/tune_holistic.py
yaqc_cmds/somatic/modules/tune_intensity.py
yaqc_cmds/somatic/modules/tune_setpoint.py
yaqc_cmds/somatic/modules/tune_test.py
yaqc_cmds/somatic/modules/zero_tune.py
yaqc_cmds/somatic/order/__init__.py
yaqc_cmds/somatic/order/ndindex.py
yaqc_cmds-2022.3.0.dist-info/entry_points.txt
yaqc_cmds-2022.3.0.dist-info/LICENSE
yaqc_cmds-2022.3.0.dist-info/WHEEL
yaqc_cmds-2022.3.0.dist-info/METADATA
yaqc_cmds-2022.3.0.dist-info/RECORD
