Metadata-Version: 2.1
Name: yaqc-cmds
Version: 2022.3.0
Summary: Unified software for controlling hardware and collecting data in the Wright group.
Home-page: https://github.com/wright-group/yaqc-cmds
Author: Blaise Thompson
Author-email: blaise@untzag.com
Requires-Python: >=3.7
Classifier: License :: OSI Approved :: MIT License
Requires-Dist: appdirs
Requires-Dist: attune
Requires-Dist: click
Requires-Dist: numexpr
Requires-Dist: pyqtgraph
Requires-Dist: pyside2
Requires-Dist: pyserial
Requires-Dist: qtpy
Requires-Dist: slackclient<2
Requires-Dist: slacker
Requires-Dist: sympy
Requires-Dist: toml
Requires-Dist: wrighttools
Requires-Dist: yaqc
